odoo/addons/stock_remote_measure/README.rst
odoo/addons/stock_remote_measure/__init__.py
odoo/addons/stock_remote_measure/__manifest__.py
odoo/addons/stock_remote_measure/i18n/it.po
odoo/addons/stock_remote_measure/i18n/stock_remote_measure.pot
odoo/addons/stock_remote_measure/models/__init__.py
odoo/addons/stock_remote_measure/models/stock_move_line.py
odoo/addons/stock_remote_measure/models/stock_picking.py
odoo/addons/stock_remote_measure/models/stock_picking_type.py
odoo/addons/stock_remote_measure/readme/CONFIGURE.rst
odoo/addons/stock_remote_measure/readme/CONTRIBUTORS.rst
odoo/addons/stock_remote_measure/readme/DESCRIPTION.rst
odoo/addons/stock_remote_measure/readme/ROADMAP.rst
odoo/addons/stock_remote_measure/readme/USAGE.rst
odoo/addons/stock_remote_measure/static/description/icon.png
odoo/addons/stock_remote_measure/static/description/index.html
odoo/addons/stock_remote_measure/views/stock_move_line_views.xml
odoo/addons/stock_remote_measure/views/stock_picking_type_views.xml
odoo/addons/stock_remote_measure/views/stock_picking_views.xml
odoo_addon_stock_remote_measure-15.0.1.0.0.5.dist-info/METADATA
odoo_addon_stock_remote_measure-15.0.1.0.0.5.dist-info/WHEEL
odoo_addon_stock_remote_measure-15.0.1.0.0.5.dist-info/top_level.txt
odoo_addon_stock_remote_measure-15.0.1.0.0.5.dist-info/RECORD
