Metadata-Version: 2.1
Name: odoo-addon-stock_remote_measure
Version: 15.0.1.0.0.5
Summary: Allows to connect to remote devices to record measures in stock fields
Home-page: https://github.com/OCA/stock-logistics-workflow
Author: Tecnativa, Odoo Community Association (OCA)
Author-email: support@odoo-community.org
License: AGPL-3
Classifier: Programming Language :: Python
Classifier: Framework :: Odoo
Classifier: Framework :: Odoo :: 15.0
Classifier: License :: OSI Approved :: GNU Affero General Public License v3
Requires-Python: >=3.8
Requires-Dist: odoo-addon-web-widget-remote-measure <15.1dev,>=15.0dev
Requires-Dist: odoo <15.1dev,>=15.0a
